Workbook

Sheet DASHBOARD
B2: 📊 DASHBOARD
B3: Auto-compute lahat — wag i-edit ang mga numbers dito
B5: TOTAL SALES (₱) | E5: TOTAL GROSS PROFIT (₱)
B6: =SUM('SALES LOG'!E2:E201) | E6: =SUM('SALES LOG'!G2:G201)
B8: TOTAL EXPENSES (₱) | E8: NET (profit − expenses) (₱)
B9: =SUM(EXPENSES!D2:D201) | E9: =SUM('SALES LOG'!G2:G201)-SUM(EXPENSES!D2:D201)
B11: INVENTORY VALUE (₱) | E11: UTANG NA HINDI PAID (₱)
B12: =SUM(INVENTORY!H2:H201) | E12: =SUMIFS(UTANG!D2:D201,UTANG!F2:F201,"<>Yes",UTANG!A2:A201,"<>")
B14: ITEMS NA REORDER NA | E14: MGA UTANG NA LATE
B15: =COUNTIF(INVENTORY!J2:J201,"⚠️ REORDER NA!") | E15: =COUNTIF(UTANG!H2:H201,"🔴 KULIKAHIN NA!")
B17: TOTAL PER ITEM (sales): | E17: TOP BUYERS (utang):
B18: Item | C18: Sales (₱)
B19: =IF(INVENTORY!A2="","",INVENTORY!A2) | C19: =IF(INVENTORY!A2="","",SUMIF('SALES LOG'!B:B,INVENTORY!A2,'SALES LOG'!E:E))
B20: =IF(INVENTORY!A3="","",INVENTORY!A3) | C20: =IF(INVENTORY!A3="","",SUMIF('SALES LOG'!B:B,INVENTORY!A3,'SALES LOG'!E:E))
B21: =IF(INVENTORY!A4="","",INVENTORY!A4) | C21: =IF(INVENTORY!A4="","",SUMIF('SALES LOG'!B:B,INVENTORY!A4,'SALES LOG'!E:E))
B22: =IF(INVENTORY!A5="","",INVENTORY!A5) | C22: =IF(INVENTORY!A5="","",SUMIF('SALES LOG'!B:B,INVENTORY!A5,'SALES LOG'!E:E))
B23: =IF(INVENTORY!A6="","",INVENTORY!A6) | C23: =IF(INVENTORY!A6="","",SUMIF('SALES LOG'!B:B,INVENTORY!A6,'SALES LOG'!E:E))
B24: =IF(INVENTORY!A7="","",INVENTORY!A7) | C24: =IF(INVENTORY!A7="","",SUMIF('SALES LOG'!B:B,INVENTORY!A7,'SALES LOG'!E:E))
B25: =IF(INVENTORY!A8="","",INVENTORY!A8) | C25: =IF(INVENTORY!A8="","",SUMIF('SALES LOG'!B:B,INVENTORY!A8,'SALES LOG'!E:E))
B26: =IF(INVENTORY!A9="","",INVENTORY!A9) | C26: =IF(INVENTORY!A9="","",SUMIF('SALES LOG'!B:B,INVENTORY!A9,'SALES LOG'!E:E))
B27: =IF(INVENTORY!A10="","",INVENTORY!A10) | C27: =IF(INVENTORY!A10="","",SUMIF('SALES LOG'!B:B,INVENTORY!A10,'SALES LOG'!E:E))
B28: =IF(INVENTORY!A11="","",INVENTORY!A11) | C28: =IF(INVENTORY!A11="","",SUMIF('SALES LOG'!B:B,INVENTORY!A11,'SALES LOG'!E:E))

Sheet README
B2: NEGOSYOSHEET — Inventory, Utang at Profit Tracker
B3: Para sa sari-sari store, online reseller, at maliliit na negosyo
B5: PAANO GAMITIN (3 steps lang):
B6: 1. I-fill ang INVENTORY sheet — item name, cost, selling price, stock-in, at reorder point.
B7: 2. I-log ang bawat benta sa SALES LOG (may dropdown na item list, auto-compute ang profit).
B8: 3. I-log ang utang sa UTANG at mga gastos sa EXPENSES. Watch ang DASHBOARD — lahat nandoon.
B10: MGA SHEET:
B11: • DASHBOARD — total sales, profit, inventory value, utang, at reorder alerts. Dito ang summary.
B12: • INVENTORY — listahan ng items. Auto-compute: current stock, stock value, REORDER NA alert.
B13: • SALES LOG — bawat sale. Auto: unit price (galing Inventory), total, cost, profit.
B14: • UTANG — listahan ng mga utang. Auto: days overdue at KULIKAHIN NA! alert.
B15: • EXPENSES — kuryente, upa, load, at iba. Ibaon sa DASHBOARD computation.
... B22: NegosyoSheet v1.0 · 2026-08-22 · Support: check README sa page where you downloaded

Sheet INVENTORY
A1: Item Name | B1: Unit | C1: Cost (₱) | D1: Selling Price (₱) | E1: Stock In | F1: Stock Out | G1: Current Stock | H1: Stock Value (₱) | I1: Reorder Point | J1: Status
A2: Noka Noodles | B2: pc | C2: 12 | D2: 18 | E2: 48 | F2: 12 | G2: =IF(A2="","",E2-F2) | H2: =IF(A2="","",G2*C2) | J2: =IF(A2="","",IF(G2<=I2,"⚠️ REORDER NA!","OK"))
A3: Softdrinks 1L | B3: btl | C3: 68 | D3: 90 | E3: 24 | F3: 5 | G3: =IF(A3="","",E3-F3) | H3: =IF(A3="","",G3*C3) | J3: =IF(A3="","",IF(G3<=I3,"⚠️ REORDER NA!","OK"))
A4: Sabon 60g | B4: pc | C4: 22 | D4: 35 | E4: 30 | F4: 8 | G4: =IF(A4="","",E4-F4) | H4: =IF(A4="","",G4*C4) | J4: =IF(A4="","",IF(G4<=I4,"⚠️ REORDER NA!","OK"))
G5: =IF(A5="","",E5-F5) | H5: =IF(A5="","",G5*C5) | J5: =IF(A5="","",IF(G5<=I5,"⚠️ REORDER NA!","OK"))
G6: =IF(A6="","",E6-F6) | H6: =IF(A6="","",G6*C6) | J6: =IF(A6="","",IF(G6<=I6,"⚠️ REORDER NA!","OK"))
G7: =IF(A7="","",E7-F7) | H7: =IF(A7="","",G7*C7) | J7: =IF(A7="","",IF(G7<=I7,"⚠️ REORDER NA!","OK"))
G8: =IF(A8="","",E8-F8) | H8: =IF(A8="","",G8*C8) | J8: =IF(A8="","",IF(G8<=I8,"⚠️ REORDER NA!","OK"))
G9: =IF(A9="","",E9-F9) | H9: =IF(A9="","",G9*C9) | J9: =IF(A9="","",IF(G9<=I9,"⚠️ REORDER NA!","OK"))
G10: =IF(A10="","",E10-F10) | H10: =IF(A10="","",G10*C10) | J10: =IF(A10="","",IF(G10<=I10,"⚠️ REORDER NA!","OK"))
G11: =IF(A11="","",E11-F11) | H11: =IF(A11="","",G11*C11) | J11: =IF(A11="","",IF(G11<=I11,"⚠️ REORDER NA!","OK"))
G12: =IF(A12="","",E12-F12) | H12: =IF(A12="","",G12*C12) | J12: =IF(A12="","",IF(G12<=I12,"⚠️ REORDER NA!","OK"))
G13: =IF(A13="","",E13-F13) | H13: =IF(A13="","",G13*C13) | J13: =IF(A13="","",IF(G13<=I13,"⚠️ REORDER NA!","OK"))
G14: =IF(A14="","",E14-F14) | H14: =IF(A14="","",G14*C14) | J14: =IF(A14="","",IF(G14<=I14,"⚠️ REORDER NA!","OK"))
G15: =IF(A15="","",E15-F15) | H15: =IF(A15="","",G15*C15) | J15: =IF(A15="","",IF(G15<=I15,"⚠️ REORDER NA!","OK"))
G16: =IF(A16="","",E16-F16) | H16: =IF(A16="","",G16*C16) | J16: =IF(A16="","",IF(G16<=I16,"⚠️ REORDER NA!","OK"))
... G201: =IF(A201="","",E201-F201) | H201: =IF(A201="","",G201*C201) | J201: =IF(A201="","",IF(G201<=I201,"⚠️ REORDER NA!","OK"))

Sheet SALES LOG
A1: Date | B1: Item Name | C1: Qty | D1: Unit Price (₱) | E1: Total (₱) | F1: Cost (₱) | G1: Profit (₱)
A2: 2026-08-22 | B2: Noka Noodles | C2: 3 | D2: =IF(OR(B2="",C2=""),"",IFERROR(VLOOKUP(B2,INVENTORY!A:D,4,FALSE),"")) | E2: =IF(OR(B2="",C2=""),"",D2*C2) | F2: =IF(OR(B2="",C2=""),"",IFERROR(VLOOKUP(B2,INVENTORY!A:C,3,FALSE),"")*C2) | G2: =IF(OR(B2="",C2=""),"",E2-F2)
A3: 2026-08-22 | B3: Softdrinks 1L | C3: 1 | D3: =IF(OR(B3="",C3=""),"",IFERROR(VLOOKUP(B3,INVENTORY!A:D,4,FALSE),"")) | E3: =IF(OR(B3="",C3=""),"",D3*C3) | F3: =IF(OR(B3="",C3=""),"",IFERROR(VLOOKUP(B3,INVENTORY!A:C,3,FALSE),"")*C3) | G3: =IF(OR(B3="",C3=""),"",E3-F3)
D4: =IF(OR(B4="",C4=""),"",IFERROR(VLOOKUP(B4,INVENTORY!A:D,4,FALSE),"")) | E4: =IF(OR(B4="",C4=""),"",D4*C4) | F4: =IF(OR(B4="",C4=""),"",IFERROR(VLOOKUP(B4,INVENTORY!A:C,3,FALSE),"")*C4) | G4: =IF(OR(B4="",C4=""),"",E4-F4)
D5: =IF(OR(B5="",C5=""),"",IFERROR(VLOOKUP(B5,INVENTORY!A:D,4,FALSE),"")) | E5: =IF(OR(B5="",C5=""),"",D5*C5) | F5: =IF(OR(B5="",C5=""),"",IFERROR(VLOOKUP(B5,INVENTORY!A:C,3,FALSE),"")*C5) | G5: =IF(OR(B5="",C5=""),"",E5-F5)
D6: =IF(OR(B6="",C6=""),"",IFERROR(VLOOKUP(B6,INVENTORY!A:D,4,FALSE),"")) | E6: =IF(OR(B6="",C6=""),"",D6*C6) | F6: =IF(OR(B6="",C6=""),"",IFERROR(VLOOKUP(B6,INVENTORY!A:C,3,FALSE),"")*C6) | G6: =IF(OR(B6="",C6=""),"",E6-F6)
D7: =IF(OR(B7="",C7=""),"",IFERROR(VLOOKUP(B7,INVENTORY!A:D,4,FALSE),"")) | E7: =IF(OR(B7="",C7=""),"",D7*C7) | F7: =IF(OR(B7="",C7=""),"",IFERROR(VLOOKUP(B7,INVENTORY!A:C,3,FALSE),"")*C7) | G7: =IF(OR(B7="",C7=""),"",E7-F7)
D8: =IF(OR(B8="",C8=""),"",IFERROR(VLOOKUP(B8,INVENTORY!A:D,4,FALSE),"")) | E8: =IF(OR(B8="",C8=""),"",D8*C8) | F8: =IF(OR(B8="",C8=""),"",IFERROR(VLOOKUP(B8,INVENTORY!A:C,3,FALSE),"")*C8) | G8: =IF(OR(B8="",C8=""),"",E8-F8)
D9: =IF(OR(B9="",C9=""),"",IFERROR(VLOOKUP(B9,INVENTORY!A:D,4,FALSE),"")) | E9: =IF(OR(B9="",C9=""),"",D9*C9) | F9: =IF(OR(B9="",C9=""),"",IFERROR(VLOOKUP(B9,INVENTORY!A:C,3,FALSE),"")*C9) | G9: =IF(OR(B9="",C9=""),"",E9-F9)
D10: =IF(OR(B10="",C10=""),"",IFERROR(VLOOKUP(B10,INVENTORY!A:D,4,FALSE),"")) | E10: =IF(OR(B10="",C10=""),"",D10*C10) | F10: =IF(OR(B10="",C10=""),"",IFERROR(VLOOKUP(B10,INVENTORY!A:C,3,FALSE),"")*C10) | G10: =IF(OR(B10="",C10=""),"",E10-F10)
D11: =IF(OR(B11="",C11=""),"",IFERROR(VLOOKUP(B11,INVENTORY!A:D,4,FALSE),"")) | E11: =IF(OR(B11="",C11=""),"",D11*C11) | F11: =IF(OR(B11="",C11=""),"",IFERROR(VLOOKUP(B11,INVENTORY!A:C,3,FALSE),"")*C11) | G11: =IF(OR(B11="",C11=""),"",E11-F11)
D12: =IF(OR(B12="",C12=""),"",IFERROR(VLOOKUP(B12,INVENTORY!A:D,4,FALSE),"")) | E12: =IF(OR(B12="",C12=""),"",D12*C12) | F12: =IF(OR(B12="",C12=""),"",IFERROR(VLOOKUP(B12,INVENTORY!A:C,3,FALSE),"")*C12) | G12: =IF(OR(B12="",C12=""),"",E12-F12)
D13: =IF(OR(B13="",C13=""),"",IFERROR(VLOOKUP(B13,INVENTORY!A:D,4,FALSE),"")) | E13: =IF(OR(B13="",C13=""),"",D13*C13) | F13: =IF(OR(B13="",C13=""),"",IFERROR(VLOOKUP(B13,INVENTORY!A:C,3,FALSE),"")*C13) | G13: =IF(OR(B13="",C13=""),"",E13-F13)
D14: =IF(OR(B14="",C14=""),"",IFERROR(VLOOKUP(B14,INVENTORY!A:D,4,FALSE),"")) | E14: =IF(OR(B14="",C14=""),"",D14*C14) | F14: =IF(OR(B14="",C14=""),"",IFERROR(VLOOKUP(B14,INVENTORY!A:C,3,FALSE),"")*C14) | G14: =IF(OR(B14="",C14=""),"",E14-F14)
D15: =IF(OR(B15="",C15=""),"",IFERROR(VLOOKUP(B15,INVENTORY!A:D,4,FALSE),"")) | E15: =IF(OR(B15="",C15=""),"",D15*C15) | F15: =IF(OR(B15="",C15=""),"",IFERROR(VLOOKUP(B15,INVENTORY!A:C,3,FALSE),"")*C15) | G15: =IF(OR(B15="",C15=""),"",E15-F15)
... D201: =IF(OR(B201="",C201=""),"",IFERROR(VLOOKUP(B201,INVENTORY!A:D,4,FALSE),"")) | E201: =IF(OR(B201="",C201=""),"",D201*C201) | F201: =IF(OR(B201="",C201=""),"",IFERROR(VLOOKUP(B201,INVENTORY!A:C,3,FALSE),"")*C201) | G201: =IF(OR(B201="",C201=""),"",E201-F201)

Sheet UTANG
A1: Date | B1: Customer | C1: Item / Notes | D1: Amount (₱) | E1: Due Date | F1: Paid? | G1: Days Overdue | H1: Status
G2: =IF(OR(E2="",F2="Yes"),"",MAX(0,TODAY()-E2)) | H2: =IF(F2="Yes","✅ PAID",IF(A2="","",IF(G2>0,"🔴 KULIKAHIN NA!","🕒 Hindi pa due")))
G3: =IF(OR(E3="",F3="Yes"),"",MAX(0,TODAY()-E3)) | H3: =IF(F3="Yes","✅ PAID",IF(A3="","",IF(G3>0,"🔴 KULIKAHIN NA!","🕒 Hindi pa due")))
G4: =IF(OR(E4="",F4="Yes"),"",MAX(0,TODAY()-E4)) | H4: =IF(F4="Yes","✅ PAID",IF(A4="","",IF(G4>0,"🔴 KULIKAHIN NA!","🕒 Hindi pa due")))
G5: =IF(OR(E5="",F5="Yes"),"",MAX(0,TODAY()-E5)) | H5: =IF(F5="Yes","✅ PAID",IF(A5="","",IF(G5>0,"🔴 KULIKAHIN NA!","🕒 Hindi pa due")))
G6: =IF(OR(E6="",F6="Yes"),"",MAX(0,TODAY()-E6)) | H6: =IF(F6="Yes","✅ PAID",IF(A6="","",IF(G6>0,"🔴 KULIKAHIN NA!","🕒 Hindi pa due")))
G7: =IF(OR(E7="",F7="Yes"),"",MAX(0,TODAY()-E7)) | H7: =IF(F7="Yes","✅ PAID",IF(A7="","",IF(G7>0,"🔴 KULIKAHIN NA!","🕒 Hindi pa due")))
G8: =IF(OR(E8="",F8="Yes"),"",MAX(0,TODAY()-E8)) | H8: =IF(F8="Yes","✅ PAID",IF(A8="","",IF(G8>0,"🔴 KULIKAHIN NA!","🕒 Hindi pa due")))
G9: =IF(OR(E9="",F9="Yes"),"",MAX(0,TODAY()-E9)) | H9: =IF(F9="Yes","✅ PAID",IF(A9="","",IF(G9>0,"🔴 KULIKAHIN NA!","🕒 Hindi pa due")))
G10: =IF(OR(E10="",F10="Yes"),"",MAX(0,TODAY()-E10)) | H10: =IF(F10="Yes","✅ PAID",IF(A10="","",IF(G10>0,"🔴 KULIKAHIN NA!","🕒 Hindi pa due")))
G11: =IF(OR(E11="",F11="Yes"),"",MAX(0,TODAY()-E11)) | H11: =IF(F11="Yes","✅ PAID",IF(A11="","",IF(G11>0,"🔴 KULIKAHIN NA!","🕒 Hindi pa due")))
G12: =IF(OR(E12="",F12="Yes"),"",MAX(0,TODAY()-E12)) | H12: =IF(F12="Yes","✅ PAID",IF(A12="","",IF(G12>0,"🔴 KULIKAHIN NA!","🕒 Hindi pa due")))
G13: =IF(OR(E13="",F13="Yes"),"",MAX(0,TODAY()-E13)) | H13: =IF(F13="Yes","✅ PAID",IF(A13="","",IF(G13>0,"🔴 KULIKAHIN NA!","🕒 Hindi pa due")))
... G201: =IF(OR(E201="",F201="Yes"),"",MAX(0,TODAY()-E201)) | H201: =IF(F201="Yes","✅ PAID",IF(A201="","",IF(G201>0,"🔴 KULIKAHIN NA!","🕒 Hindi pa due")))

Sheet EXPENSES
A1: Date | B1: Category | C1: Description | D1: Amount (₱)
